{
  "id": 1763136852932,
  "slug": "mobile-design",
  "title": "Mobile App Design Best Practices for 2025",
  "author": "CoderDesign Team",
  "category": "Mobile App Development",
  "image": "/uploads/1763136852914-Mobile_Design.jfif",
  "createdAt": "2025-11-14T16:14:12.916Z",
  "short_description": "Essential mobile app design best practices for 2025 covering UI/UX principles, touch interactions, accessibility, responsive layouts, and design systems for iOS and Android apps.",
  "readTime": 7
}
